py_own_synonyms_pkg/__init__.py
py_own_synonyms_pkg/synonyms.json
py_own_synonyms_pkg-0.1.6.dist-info/LICENSE
py_own_synonyms_pkg-0.1.6.dist-info/METADATA
py_own_synonyms_pkg-0.1.6.dist-info/WHEEL
py_own_synonyms_pkg-0.1.6.dist-info/top_level.txt
py_own_synonyms_pkg-0.1.6.dist-info/RECORD
