Metadata-Version: 2.1
Name: py-own-synonyms-pkg
Version: 0.1.6
Classifier: Programming Language :: Python :: 3
Classifier: License :: OSI Approved :: MIT License
Classifier: Operating System :: OS Independent
Requires-Python: >=3.10
License-File: LICENSE
